tkchart/FontStyle.py
tkchart/Line.py
tkchart/LineChart.py
tkchart/Utils.py
tkchart/Validate.py
tkchart/__init__.py
tkchart-2.1.8.dist-info/licenses/LICENSE
tkchart-2.1.8.dist-info/METADATA
tkchart-2.1.8.dist-info/WHEEL
tkchart-2.1.8.dist-info/top_level.txt
tkchart-2.1.8.dist-info/RECORD
