Metadata-Version: 2.4
Name: tkchart
Version: 2.1.8
Summary: Python library for creating live updating line charts in Tkinter.
Author: Thisal-D
License: Copyright (c) 2024 The Python Packaging Authority
Project-URL: homepage, https://github.com/Thisal-D/tkchart
Project-URL: repository, https://github.com/Thisal-D/tkchart
Project-URL: issues, https://github.com/Thisal-D/tkchart/issues
Keywords: tkchart,ctkchart,linechart,ctk linechart,tk linechart,tkinter,customtkinter,line chart in tkinter,line chart in customtkinter,customtkinter graphic-interface,tkinter graphic interface,tkinter widgets,customtkinter widgets,python-chart,tk,ctk,customtkinterassets,tkinterassets,ctk-components,tk-components,line-chart-for-python-tkinter,line-chart-for-python-customtkinter
Classifier: Programming Language :: Python :: 3
Classifier: Operating System :: OS Independent
Classifier: Development Status :: 5 - Production/Stable
Requires-Python: >=3.0
License-File: LICENSE
Dynamic: license-file
